rbnf/__init__.py
rbnf/__release_info__.py
rbnf/_literal_matcher.py
rbnf/cli.py
rbnf/color.py
rbnf/easy.py
rbnf/err.py
rbnf/auto_lexer/__init__.py
rbnf/auto_lexer/rbnf_lexer.py
rbnf/bootstrap/__init__.py
rbnf/bootstrap/loader.py
rbnf/bootstrap/rbnf.py
rbnf/core/AST.py
rbnf/core/CachingPool.py
rbnf/core/Optimize.py
rbnf/core/ParserC.py
rbnf/core/ParserC.pyi
rbnf/core/Result.py
rbnf/core/State.py
rbnf/core/Tokenizer.py
rbnf/core/Tokenizer.pyi
rbnf/core/Trace.py
rbnf/core/__init__.py
rbnf/core/parser_algo/__init__.py
rbnf/core/parser_algo/for_atom.py
rbnf/core/parser_algo/for_composed.py
rbnf/edsl/__init__.py
rbnf/edsl/core.py
rbnf/edsl/core.pyi
rbnf/edsl/rbnf_analyze.py
rbnf/py_tools/__init__.py
rbnf/py_tools/unparse.py
rbnf/rbnf_libs/std/common.rbnf
rbnf/std/__init__.py
rbnf/std/common.py
rbnf/std/xml.py
rbnf/zero/__init__.py
rbnf/zero/impl.py
rbnf/zero/impl.pyi
rbnf/zero/user_interface.py
rbnf/zero/user_interface.pyi
rbnf-0.3.21.dist-info/METADATA
rbnf-0.3.21.dist-info/RECORD
rbnf-0.3.21.dist-info/WHEEL
rbnf-0.3.21.dist-info/entry_points.txt
rbnf-0.3.21.dist-info/top_level.txt
