Metadata-Version: 2.1
Name: rbnf
Version: 0.3.21
Summary: context sensitive grammar parser generator for CPython
Home-page: https://github.com/thautwarm/Ruiko
Author: thautwarm
Author-email: twshere@outlook.com
License: MIT
Keywords: parser-generator,context-sensitive,ebnf
Platform: any
Classifier: Programming Language :: Python :: 3.6
Classifier: Programming Language :: Python :: 3.7
Classifier: Programming Language :: Python :: Implementation :: CPython
Requires-Python: >=3.6.0
Requires-Dist: linq-t (>=0.1)
Requires-Dist: Redy (>=0.2.2)
Requires-Dist: wisepy (>=0.2.8)
